vibedna/__init__.py
vibedna/py.typed
vibedna/agents/__init__.py
vibedna/agents/base/__init__.py
vibedna/agents/base/agent_base.py
vibedna/agents/base/context.py
vibedna/agents/base/message.py
vibedna/agents/base/tool.py
vibedna/agents/mcp_servers/__init__.py
vibedna/agents/mcp_servers/base_server.py
vibedna/agents/mcp_servers/compute_server.py
vibedna/agents/mcp_servers/core_server.py
vibedna/agents/mcp_servers/fs_server.py
vibedna/agents/mcp_servers/monitor_server.py
vibedna/agents/mcp_servers/search_server.py
vibedna/agents/mcp_servers/synth_server.py
vibedna/agents/orchestration/__init__.py
vibedna/agents/orchestration/master_orchestrator.py
vibedna/agents/orchestration/resource_orchestrator.py
vibedna/agents/orchestration/workflow_orchestrator.py
vibedna/agents/protocols/__init__.py
vibedna/agents/protocols/compute_workflow.py
vibedna/agents/protocols/decode_workflow.py
vibedna/agents/protocols/encode_workflow.py
vibedna/agents/skills/__init__.py
vibedna/agents/skills/encoding_skill.py
vibedna/agents/skills/error_correction_skill.py
vibedna/agents/specialist/__init__.py
vibedna/agents/specialist/compute_agent.py
vibedna/agents/specialist/decoder_agent.py
vibedna/agents/specialist/encoder_agent.py
vibedna/agents/specialist/error_correction_agent.py
vibedna/agents/specialist/filesystem_agent.py
vibedna/agents/specialist/synthesis_agent.py
vibedna/agents/specialist/validation_agent.py
vibedna/agents/specialist/visualization_agent.py
vibedna/agents/support/__init__.py
vibedna/agents/support/docs_agent.py
vibedna/agents/support/index_agent.py
vibedna/agents/support/logging_agent.py
vibedna/agents/support/metrics_agent.py
vibedna/agents/support/security_agent.py
vibedna/api/__init__.py
vibedna/api/rest_server.py
vibedna/api/schemas.py
vibedna/cli/__init__.py
vibedna/cli/formatters.py
vibedna/cli/vibedna_cli.py
vibedna/cli/commands/__init__.py
vibedna/compute/__init__.py
vibedna/compute/dna_arithmetic.py
vibedna/compute/dna_logic_gates.py
vibedna-1.0.0.dist-info/METADATA
vibedna-1.0.0.dist-info/WHEEL
vibedna-1.0.0.dist-info/entry_points.txt
vibedna-1.0.0.dist-info/licenses/LICENSE
vibedna-1.0.0.dist-info/RECORD
