Metadata-Version: 2.4
Name: vibedna
Version: 1.0.0
Summary: Binary ↔ DNA Encoding and Computation System - Convert data to DNA sequences and back
Project-URL: Homepage, https://vibecaas.com
Project-URL: Documentation, https://github.com/ttracx/VibeDNA#readme
Project-URL: Repository, https://github.com/ttracx/VibeDNA
Project-URL: Issues, https://github.com/ttracx/VibeDNA/issues
Project-URL: Changelog, https://github.com/ttracx/VibeDNA/blob/main/CHANGELOG.md
Author-email: "NeuralQuantum.ai" <contact@neuralquantum.ai>
Maintainer-email: "NeuralQuantum.ai" <contact@neuralquantum.ai>
License: Proprietary
License-File: LICENSE
Keywords: binary-to-dna,bioinformatics,data-storage,decoding,dna,dna-computing,dna-to-binary,encoding,error-correction,nucleotide,reed-solomon,sequence
Classifier: Development Status :: 4 - Beta
Classifier: Environment :: Console
Classifier: Framework :: FastAPI
Classifier: Intended Audience :: Developers
Classifier: Intended Audience :: Science/Research
Classifier: Operating System :: OS Independent
Classifier: Programming Language :: Python :: 3
Classifier: Programming Language :: Python :: 3 :: Only
Classifier: Programming Language :: Python :: 3.10
Classifier: Programming Language :: Python :: 3.11
Classifier: Programming Language :: Python :: 3.12
Classifier: Topic :: Scientific/Engineering :: Bio-Informatics
Classifier: Topic :: Scientific/Engineering :: Information Analysis
Classifier: Topic :: System :: Archiving
Classifier: Typing :: Typed
Requires-Python: >=3.10
Requires-Dist: click>=8.0
Requires-Dist: fastapi>=0.100
Requires-Dist: numpy>=1.24
Requires-Dist: pydantic>=2.0
Requires-Dist: rich>=13.0
Requires-Dist: uvicorn>=0.23
Provides-Extra: dev
Requires-Dist: black>=23.0; extra == 'dev'
Requires-Dist: mypy>=1.4; extra == 'dev'
Requires-Dist: pytest-asyncio>=0.21; extra == 'dev'
Requires-Dist: pytest-cov>=4.0; extra == 'dev'
Requires-Dist: pytest>=7.0; extra == 'dev'
Requires-Dist: ruff>=0.0.280; extra == 'dev'
